patroni_monitoring/__init__.py
patroni_monitoring/arguments.py
patroni_monitoring/cli.py
patroni_monitoring/constants.py
patroni_monitoring/monitoring.py
patroni_monitoring/patroni.py
patroni_monitoring/py.typed
patroni_monitoring-1.0.0.dist-info/METADATA
patroni_monitoring-1.0.0.dist-info/WHEEL
patroni_monitoring-1.0.0.dist-info/entry_points.txt
patroni_monitoring-1.0.0.dist-info/RECORD
