Metadata-Version: 2.4
Name: patroni-monitoring
Version: 1.0.0
Summary: Patroni monitoring tool
Requires-Python: >=3.9
Requires-Dist: httpx>=0.28.1
Requires-Dist: tabulate>=0.9.0
